skepticoin/__init__.py
skepticoin/__version__.py
skepticoin/cheating.py
skepticoin/coinstate.py
skepticoin/consensus.py
skepticoin/datatypes.py
skepticoin/explorer.py
skepticoin/genesis.py
skepticoin/hash.py
skepticoin/humans.py
skepticoin/merkletree.py
skepticoin/mining.py
skepticoin/params.py
skepticoin/pow.py
skepticoin/scmversion.py
skepticoin/serialization.py
skepticoin/signing.py
skepticoin/utils.py
skepticoin/wallet.py
skepticoin/networking/__init__.py
skepticoin/networking/disk_interface.py
skepticoin/networking/local_peer.py
skepticoin/networking/manager.py
skepticoin/networking/messages.py
skepticoin/networking/params.py
skepticoin/networking/remote_peer.py
skepticoin/networking/threading.py
skepticoin/scripts/__init__.py
skepticoin/scripts/balance.py
skepticoin/scripts/mine.py
skepticoin/scripts/receive.py
skepticoin/scripts/repl.py
skepticoin/scripts/run.py
skepticoin/scripts/send.py
skepticoin/scripts/utils.py
skepticoin/scripts/version.py
skepticoin-3.0.0.dist-info/LICENSE
skepticoin-3.0.0.dist-info/METADATA
skepticoin-3.0.0.dist-info/WHEEL
skepticoin-3.0.0.dist-info/entry_points.txt
skepticoin-3.0.0.dist-info/top_level.txt
skepticoin-3.0.0.dist-info/RECORD
