Metadata-Version: 2.1
Name: skepticoin
Version: 3.0.0
Summary: The Coin for Non-Believers
Home-page: https://www.skepticoin.org/
Author: Sashimi Houdini
Author-email: pandas-dev@python.org
License: BSD-3-Clause
Project-URL: Github, https://github.com/skepticoin/skepticoin/
Project-URL: Reddit, https://reddit.com/r/skepticoin
Project-URL: Twitter, https://www.twitter.com/Skepticoinz
Platform: any
Classifier: Development Status :: 4 - Beta
Classifier: Environment :: Console
Classifier: Intended Audience :: End Users/Desktop
Classifier: Intended Audience :: Developers
Classifier: License :: OSI Approved :: BSD License
Classifier: Operating System :: MacOS :: MacOS X
Classifier: Operating System :: Microsoft :: Windows
Classifier: Operating System :: POSIX
Classifier: Programming Language :: Python
Requires-Python: >=3.7.*
Requires-Dist: ecdsa (>=0.16.1)
Requires-Dist: immutables (>=0.15)
Requires-Dist: ptpython
Requires-Dist: scrypt (>=0.8.17)
Provides-Extra: test
Requires-Dist: hypothesis (>=5.5.3) ; extra == 'test'
Requires-Dist: pytest-xdist (>=1.31) ; extra == 'test'
Requires-Dist: pytest (>=6.0) ; extra == 'test'
